androtools/__init__.py
androtools/__main__.py
androtools/android_sdk/__init__.py
androtools/android_sdk/avdmanager.py
androtools/android_sdk/build_tools.py
androtools/android_sdk/cmdline_tools.py
androtools/android_sdk/emulator.py
androtools/android_sdk/platform_tools.py
androtools/cmd/__init__.py
androtools/cmd/abc.py
androtools/cmd/result.py
androtools/core/__init__.py
androtools/core/constants.py
androtools/core/device.py
androtools/core/google.py
androtools/core/ld.py
androtools/core/nox.py
androtools/utils/__init__.py
androtools/utils/tool.py
androtools-1.0.9.dist-info/WHEEL
androtools-1.0.9.dist-info/entry_points.txt
androtools-1.0.9.dist-info/METADATA
androtools-1.0.9.dist-info/RECORD
