Metadata-Version: 2.4
Name: androtools
Version: 1.0.9
Summary: 一个对Android SDK相关的命令封装的库
Author: kin9-0rz
Author-email: kin9-0rz <kin9-0rz@outlook.com>
License-Expression: MIT
Requires-Dist: func-timeout>=4.3.5
Requires-Dist: loguru>=0.7.3
Requires-Dist: psutil>=7.1.3
Requires-Python: >=3.10
